ranimegen/__init__.py
ranimegen/animegen.py
ranimegen/errors.py
ranimegen/workers.py
ranimegen-1.0.0.dist-info/licenses/LICENSE
ranimegen-1.0.0.dist-info/METADATA
ranimegen-1.0.0.dist-info/WHEEL
ranimegen-1.0.0.dist-info/top_level.txt
ranimegen-1.0.0.dist-info/RECORD
