Metadata-Version: 2.4
Name: ranimegen
Version: 1.0.0
Summary: A python lib to generate random anime and its information
Home-page: https://github.com/Harukomaze/ranimegen
Author: Harukomaze
Author-email: sdpqwer0@gmail.com
License: MIT
Keywords: discord random-anime anime ranime random-anime-generator anime-generator
Classifier: Development Status :: 5 - Production/Stable
Classifier: Intended Audience :: Education
Classifier: Operating System :: POSIX :: Linux
Classifier: Operating System :: Microsoft :: Windows
Classifier: Operating System :: MacOS
Classifier: License :: OSI Approved :: MIT License
Classifier: Programming Language :: Python :: 3
License-File: LICENSE
Requires-Dist: aiohttp
Requires-Dist: bs4
Dynamic: author
Dynamic: author-email
Dynamic: classifier
Dynamic: description
Dynamic: description-content-type
Dynamic: home-page
Dynamic: keywords
Dynamic: license
Dynamic: license-file
Dynamic: requires-dist
Dynamic: summary
